sublinear/__init__.py
sublinear/count/__init__.py
sublinear/count/morris/__init__.py
sublinear/count/morris/morris_basic.py
sublinear/count/morris/morris_plus.py
sublinear/count/morris/morris_plus_plus.py
sublinear/count/morris/experiments/__init__.py
sublinear/count/morris/experiments/experiment1.py
sublinear/distinct_elements/__init__.py
sublinear/distinct_elements/bjkst/__init__.py
sublinear/distinct_elements/bjkst/bjkst_plus.py
sublinear/distinct_elements/bjkst/bjkst_sketch.py
sublinear/distinct_elements/bjkst/experiments/__init__.py
sublinear/distinct_elements/bjkst/experiments/experiment1.py
sublinear/distinct_elements/bjkst/experiments/experiment2.py
sublinear/distinct_elements/hyperloglog/__init__.py
sublinear/distinct_elements/hyperloglog/hyper_log_log.py
sublinear/distinct_elements/hyperloglog/experiments/__init__.py
sublinear/distinct_elements/hyperloglog/experiments/experiment1.py
sublinear/distinct_elements/sketch_switching/__init__.py
sublinear/distinct_elements/sketch_switching/sketch_switch.py
sublinear/distinct_elements/sketch_switching/experiments/__init__.py
sublinear/distinct_elements/sketch_switching/experiments/experiment1.py
sublinear/frequency_table/__init__.py
sublinear/frequency_table/cms/__init__.py
sublinear/frequency_table/cms/count_min_sketch.py
sublinear/frequency_table/cms/experiments/__init__.py
sublinear/frequency_table/cms/experiments/cms_text.py
sublinear/frequency_table/cms/experiments/experiment1.py
sublinear/frequency_table/cms/experiments/experiment2.py
sublinear/heavy_hitters/__init__.py
sublinear/heavy_hitters/mgs/__init__.py
sublinear/heavy_hitters/mgs/misra_gries_sketch.py
sublinear/heavy_hitters/mgs/experiments/__init__.py
sublinear/heavy_hitters/mgs/experiments/experiment1.py
sublinear/second_moment/__init__.py
sublinear/second_moment/ams/__init__.py
sublinear/second_moment/ams/ams_sketch_basic.py
sublinear/second_moment/ams/ams_sketch_plus.py
sublinear/second_moment/ams/ams_sketch_plus_plus.py
sublinear-0.1.0.dist-info/LICENSE
sublinear-0.1.0.dist-info/METADATA
sublinear-0.1.0.dist-info/WHEEL
sublinear-0.1.0.dist-info/top_level.txt
sublinear-0.1.0.dist-info/RECORD
