Metadata-Version: 2.1
Name: sublinear
Version: 0.1.0
Summary: Python library implementing a subset of streaming algorithms. Includes variations of these algorithms (e.g. adversarially robust), as well as support for multiple data types.
Home-page: https://github.com/ivannikitovic/sublinear
Author: Ivan Nikitovic
Author-email: ivan.bnikitovic@gmail.com
License: MIT
Requires-Python: >=3.7
License-File: LICENSE
Requires-Dist: numpy
Requires-Dist: matplotlib
